odoo8_addon_account_export_csv-8.0.1.1.0-py2.7-nspkg.pth
odoo_addons/account_export_csv/__openerp__.py
odoo_addons/account_export_csv/menu.xml
odoo_addons/account_export_csv/__init__.py
odoo_addons/account_export_csv/i18n/account_export_csv.po
odoo_addons/account_export_csv/i18n/nl.po
odoo_addons/account_export_csv/i18n/fr.po
odoo_addons/account_export_csv/wizard/account_export_csv.py
odoo_addons/account_export_csv/wizard/__init__.py
odoo_addons/account_export_csv/wizard/account_export_csv_view.xml
odoo8_addon_account_export_csv-8.0.1.1.0.dist-info/top_level.txt
odoo8_addon_account_export_csv-8.0.1.1.0.dist-info/WHEEL
odoo8_addon_account_export_csv-8.0.1.1.0.dist-info/RECORD
odoo8_addon_account_export_csv-8.0.1.1.0.dist-info/metadata.json
odoo8_addon_account_export_csv-8.0.1.1.0.dist-info/DESCRIPTION.rst
odoo8_addon_account_export_csv-8.0.1.1.0.dist-info/METADATA
odoo8_addon_account_export_csv-8.0.1.1.0.dist-info/namespace_packages.txt
